README.rst
setup.py
arcangelo/__init__.py
arcangelo/cvt_script.man
arcangelo.egg-info/PKG-INFO
arcangelo.egg-info/SOURCES.txt
arcangelo.egg-info/dependency_links.txt
arcangelo.egg-info/entry_points.txt
arcangelo.egg-info/not-zip-safe
arcangelo.egg-info/requires.txt
arcangelo.egg-info/top_level.txt
arcangelo/docs/MAINPAGE.rst
arcangelo/docs/Makefile
arcangelo/docs/__init__.txt
arcangelo/docs/conf.py
arcangelo/docs/index.rst
arcangelo/docs/logozero_180x46.png
arcangelo/docs/readthedocs.yml
arcangelo/docs/requirements.txt
arcangelo/docs/rtd_automodule.rst
arcangelo/docs/rtd_changelog.rst
arcangelo/docs/rtd_credits.rst
arcangelo/docs/rtd_description.rst
arcangelo/docs/rtd_getting_started.rst
arcangelo/docs/rtd_usage.rst
arcangelo/docs/_build/doctrees/environment.pickle
arcangelo/docs/_build/doctrees/index.doctree
arcangelo/docs/_build/doctrees/rtd_automodule.doctree
arcangelo/docs/_build/doctrees/rtd_changelog.doctree
arcangelo/docs/_build/doctrees/rtd_credits.doctree
arcangelo/docs/_build/doctrees/rtd_description.doctree
arcangelo/docs/_build/doctrees/rtd_description_arcangelo.doctree
arcangelo/docs/_build/doctrees/rtd_description_gen_readme.doctree
arcangelo/docs/_build/doctrees/rtd_description_macro.doctree
arcangelo/docs/_build/doctrees/rtd_description_odoo_dependencies.doctree
arcangelo/docs/_build/doctrees/rtd_description_please.doctree
arcangelo/docs/_build/doctrees/rtd_getting_started.doctree
arcangelo/docs/_build/doctrees/rtd_macro.doctree
arcangelo/docs/_build/doctrees/rtd_usage.doctree
arcangelo/docs/_build/doctrees/rtd_usage_arcangelo.doctree
arcangelo/docs/_build/doctrees/rtd_usage_gen_readme.doctree
arcangelo/docs/_build/doctrees/rtd_usage_gen_readme_sym.doctree
arcangelo/docs/_build/doctrees/rtd_usage_odoo_dependencies.doctree
arcangelo/docs/_build/doctrees/rtd_usage_please.doctree
arcangelo/docs/_build/html/.buildinfo
arcangelo/docs/_build/html/.nojekyll
arcangelo/docs/_build/html/genindex.html
arcangelo/docs/_build/html/index.html
arcangelo/docs/_build/html/objects.inv
arcangelo/docs/_build/html/py-modindex.html
arcangelo/docs/_build/html/rtd_automodule.html
arcangelo/docs/_build/html/rtd_changelog.html
arcangelo/docs/_build/html/rtd_credits.html
arcangelo/egg-info/CHANGELOG.rst
arcangelo/egg-info/DESCRIPTION.rst
arcangelo/egg-info/USAGE.rst
arcangelo/egg-info/__manifest__.rst
arcangelo/egg-info/rules_usage_items.csv
arcangelo/egg-info/rules_usage_items.rst
