Metadata-Version: 2.1
Name: arcangelo
Version: 2.1.1
Summary: Source code mass automatic upgrade
Home-page: https://github.com/zeroincombenze/tools
Author: Antonio Maria Vigliotti
Author-email: antoniomaria.vigliotti@gmail.com
License: GPL-3.0-or-later
Project-URL: Source, https://github.com/zeroincombenze/tools/tree/master/arcangelo
Project-URL: Documentation, https://zeroincombenze-tools.readthedocs.io/en/latest/#arcangelo
Project-URL: Changelog, https://github.com/zeroincombenze/tools/blob/master/arcangelo/egg-info/CHANGELOG.rst
Keywords: linux odoo documentation development
Platform: UNKNOWN
Classifier: Development Status :: 4 - Beta
Classifier: Operating System :: POSIX
Classifier: Programming Language :: Python :: 2.7
Classifier: Programming Language :: Python :: 3.7
Classifier: Programming Language :: Python :: 3.8
Classifier: Programming Language :: Python :: 3.9
Classifier: Programming Language :: Python :: 3.10
Classifier: Programming Language :: Python :: 3.11
Classifier: Programming Language :: Python :: 3.12
Classifier: Intended Audience :: Developers
Classifier: Topic :: Software Development
Classifier: Topic :: Software Development :: Libraries
Classifier: Topic :: Software Development :: Build Tools
Classifier: Operating System :: OS Independent
